{"_id":"mpromise","_rev":"37-1b67a86c51111398b5adfef2c40f9c74","name":"mpromise","description":"Promises A+ conformant implementation","dist-tags":{"latest":"0.5.1","beta":"0.5.4"},"versions":{"0.0.1":{"name":"mpromise","version":"0.0.1","description":"Promises A+ conformant implementation","main":"index.js","scripts":{"test":"make test"},"dependencies":{"sliced":"0.0.4"},"devDependencies":{"mocha":"1.7.4","promises-aplus-tests":">= 1.0.2"},"repository":{"type":"git","url":"git://github.com/aheckmann/mpromise"},"keywords":["promise","mongoose","aplus","a+","plus"],"author":{"name":"Aaron Heckmann","email":"aaron.heckmann+github@gmail.com"},"license":"MIT","_id":"mpromise@0.0.1","dist":{"shasum":"1319eca05ff40ca17a914a3bbba9ada267a499c0","tarball":"http://registry.npmjs.org/mpromise/-/mpromise-0.0.1.tgz"},"_npmVersion":"1.1.59","_npmUser":{"name":"aaron","email":"aaron.heckmann+github@gmail.com"},"maintainers":[{"name":"aaron","email":"aaron.heckmann+github@gmail.com"}],"directories":{}},"0.1.0":{"name":"mpromise","version":"0.1.0","description":"Promises A+ conformant implementation","main":"index.js","scripts":{"test":"make test"},"dependencies":{"sliced":"0.0.4"},"devDependencies":{"mocha":"1.7.4","promises-aplus-tests":">= 1.0.2"},"repository":{"type":"git","url":"git://github.com/aheckmann/mpromise"},"keywords":["promise","mongoose","aplus","a+","plus"],"author":{"name":"Aaron Heckmann","email":"aaron.heckmann+github@gmail.com"},"license":"MIT","_id":"mpromise@0.1.0","dist":{"shasum":"2102f48e43d9614b227f17d58af5fd1559c7bc76","tarball":"http://registry.npmjs.org/mpromise/-/mpromise-0.1.0.tgz"},"_npmVersion":"1.1.59","_npmUser":{"name":"aaron","email":"aaron.heckmann+github@gmail.com"},"maintainers":[{"name":"aaron","email":"aaron.heckmann+github@gmail.com"}],"directories":{}},"0.2.0":{"name":"mpromise","version":"0.2.0","description":"Promises A+ conformant implementation","main":"index.js","scripts":{"test":"make test"},"dependencies":{"sliced":"0.0.4"},"devDependencies":{"mocha":"1.7.4","promises-aplus-tests":">= 1.0.2"},"repository":{"type":"git","url":"git://github.com/aheckmann/mpromise"},"keywords":["promise","mongoose","aplus","a+","plus"],"author":{"name":"Aaron Heckmann","email":"aaron.heckmann+github@gmail.com"},"license":"MIT","_id":"mpromise@0.2.0","dist":{"shasum":"55f8b1f32295d1f76e18fad63cddb1d91ed4b9d6","tarball":"http://registry.npmjs.org/mpromise/-/mpromise-0.2.0.tgz"},"_npmVersion":"1.1.59","_npmUser":{"name":"aaron","email":"aaron.heckmann+github@gmail.com"},"maintainers":[{"name":"aaron","email":"aaron.heckmann+github@gmail.com"}],"directories":{}},"0.2.1":{"name":"mpromise","version":"0.2.1","description":"Promises A+ conformant implementation","main":"index.js","scripts":{"test":"make test"},"dependencies":{"sliced":"0.0.4"},"devDependencies":{"mocha":"1.7.4","promises-aplus-tests":">= 1.2"},"repository":{"type":"git","url":"git://github.com/aheckmann/mpromise"},"keywords":["promise","mongoose","aplus","a+","plus"],"author":{"name":"Aaron Heckmann","email":"aaron.heckmann+github@gmail.com"},"license":"MIT","_id":"mpromise@0.2.1","dist":{"shasum":"fbbdc28cb0207e49b8a4eb1a4c0cea6c2de794c8","tarball":"http://registry.npmjs.org/mpromise/-/mpromise-0.2.1.tgz"},"_npmVersion":"1.1.59","_npmUser":{"name":"aaron","email":"aaron.heckmann+github@gmail.com"},"maintainers":[{"name":"aaron","email":"aaron.heckmann+github@gmail.com"}],"directories":{}},"0.2.2":{"name":"mpromise","version":"0.2.2","description":"Promises A+ conformant implementation","main":"index.js","scripts":{"test":"make test"},"dependencies":{"sliced":"0.0.4"},"devDependencies":{"mocha":"1.7.4","promises-aplus-tests":"1.2"},"repository":{"type":"git","url":"git://github.com/aheckmann/mpromise"},"keywords":["promise","mongoose","aplus","a+","plus"],"author":{"name":"Aaron Heckmann","email":"aaron.heckmann+github@gmail.com"},"license":"MIT","_id":"mpromise@0.2.2","dist":{"shasum":"e8126a9a6c806f974ee971a892cb0781c14976b8","tarball":"http://registry.npmjs.org/mpromise/-/mpromise-0.2.2.tgz"},"maintainers":[{"name":"aaron","email":"aaron.heckmann+github@gmail.com"}],"directories":{}},"0.3.0":{"name":"mpromise","version":"0.3.0","description":"Promises A+ conformant implementation","main":"index.js","scripts":{"test":"make test"},"dependencies":{"sliced":"0.0.5"},"devDependencies":{"mocha":"1.7.4","promises-aplus-tests":">= 1.2"},"repository":{"type":"git","url":"git://github.com/aheckmann/mpromise"},"keywords":["promise","mongoose","aplus","a+","plus"],"author":{"name":"Aaron Heckmann","email":"aaron.heckmann+github@gmail.com"},"license":"MIT","bugs":{"url":"https://github.com/aheckmann/mpromise/issues"},"_id":"mpromise@0.3.0","dist":{"shasum":"cb864c2f642eb2192765087e3692e1dc152afe4b","tarball":"http://registry.npmjs.org/mpromise/-/mpromise-0.3.0.tgz"},"_from":".","_npmVersion":"1.2.23","_npmUser":{"name":"aaron","email":"aaron.heckmann+github@gmail.com"},"maintainers":[{"name":"aaron","email":"aaron.heckmann+github@gmail.com"}],"directories":{}},"0.4.0":{"name":"mpromise","version":"0.4.0","description":"Promises A+ conformant implementation","main":"index.js","scripts":{"test":"make test"},"dependencies":{},"devDependencies":{"mocha":"1.13.0","promises-aplus-tests":">= 2.0.0"},"repository":{"type":"git","url":"git://github.com/aheckmann/mpromise"},"keywords":["promise","mongoose","aplus","a+","plus"],"author":{"name":"Aaron Heckmann","email":"aaron.heckmann+github@gmail.com"},"license":"MIT","bugs":{"url":"https://github.com/aheckmann/mpromise/issues"},"_id":"mpromise@0.4.0","dist":{"shasum":"0553265f4d2caebda390f0ce0b2f3dcfb65fb547","tarball":"http://registry.npmjs.org/mpromise/-/mpromise-0.4.0.tgz"},"_from":".","_npmVersion":"1.2.30","_npmUser":{"name":"aaron","email":"aaron.heckmann+github@gmail.com"},"maintainers":[{"name":"aaron","email":"aaron.heckmann+github@gmail.com"}],"directories":{}},"0.4.1":{"name":"mpromise","version":"0.4.1","description":"Promises A+ conformant implementation","main":"index.js","scripts":{"test":"make test"},"dependencies":{},"devDependencies":{"mocha":"1.13.0","promises-aplus-tests":">= 2.0.0","longjohn":"0.2.1"},"repository":{"type":"git","url":"git://github.com/aheckmann/mpromise"},"keywords":["promise","mongoose","aplus","a+","plus"],"author":{"name":"Aaron Heckmann","email":"aaron.heckmann+github@gmail.com"},"license":"MIT","bugs":{"url":"https://github.com/aheckmann/mpromise/issues"},"homepage":"https://github.com/aheckmann/mpromise","_id":"mpromise@0.4.1","dist":{"shasum":"3421fe441c6726ed6c89a812ba82784a640c354b","tarball":"http://registry.npmjs.org/mpromise/-/mpromise-0.4.1.tgz"},"_from":".","_npmVersion":"1.3.11","_npmUser":{"name":"refack","email":"refael@empeeric.com"},"maintainers":[{"name":"aaron","email":"aaron.heckmann+github@gmail.com"},{"name":"refack","email":"refael@empeeric.com"}],"directories":{}},"0.4.2":{"name":"mpromise","version":"0.4.2","description":"Promises A+ conformant implementation","main":"index.js","scripts":{"test":"make test"},"dependencies":{},"devDependencies":{"mocha":"1.13.0","promises-aplus-tests":">= 2.0.0","longjohn":"0.2.1"},"repository":{"type":"git","url":"git://github.com/aheckmann/mpromise"},"keywords":["promise","mongoose","aplus","a+","plus"],"author":{"name":"Aaron Heckmann","email":"aaron.heckmann+github@gmail.com"},"license":"MIT","bugs":{"url":"https://github.com/aheckmann/mpromise/issues"},"homepage":"https://github.com/aheckmann/mpromise","_id":"mpromise@0.4.2","dist":{"shasum":"12141c3e3f6df59c35c7e9d6460380840a9e8fa0","tarball":"http://registry.npmjs.org/mpromise/-/mpromise-0.4.2.tgz"},"_from":".","_npmVersion":"1.3.13","_npmUser":{"name":"refack","email":"refael@empeeric.com"},"maintainers":[{"name":"aaron","email":"aaron.heckmann+github@gmail.com"},{"name":"refack","email":"refael@empeeric.com"}],"directories":{}},"0.5.0":{"name":"mpromise","version":"0.5.0","description":"Promises A+ conformant implementation","main":"index.js","scripts":{"test":"node node_modules/mocha/bin/_mocha"},"devDependencies":{"longjohn":"~0.2.1","promises-aplus-tests":"~2.0.2","mocha":"~1.13.0"},"repository":{"type":"git","url":"git://github.com/aheckmann/mpromise"},"keywords":["promise","mongoose","aplus","a+","plus"],"author":{"name":"Aaron Heckmann","email":"aaron.heckmann+github@gmail.com"},"license":"MIT","bugs":{"url":"https://github.com/aheckmann/mpromise/issues"},"homepage":"https://github.com/aheckmann/mpromise","_id":"mpromise@0.5.0","dist":{"shasum":"8ff8f6aba6534bffa6fff296e13348cd065091b5","tarball":"http://registry.npmjs.org/mpromise/-/mpromise-0.5.0.tgz"},"_from":".","_npmVersion":"1.3.14","_npmUser":{"name":"aaron","email":"aaron.heckmann+github@gmail.com"},"maintainers":[{"name":"aaron","email":"aaron.heckmann+github@gmail.com"},{"name":"refack","email":"refael@empeeric.com"}],"directories":{}},"0.4.3":{"name":"mpromise","version":"0.4.3","description":"Promises A+ conformant implementation","main":"index.js","scripts":{"test":"node node_modules/mocha/bin/_mocha"},"devDependencies":{"longjohn":"~0.2.1","promises-aplus-tests":"~2.0.2","mocha":"~1.13.0"},"repository":{"type":"git","url":"git://github.com/aheckmann/mpromise"},"keywords":["promise","mongoose","aplus","a+","plus"],"author":{"name":"Aaron Heckmann","email":"aaron.heckmann+github@gmail.com"},"license":"MIT","bugs":{"url":"https://github.com/aheckmann/mpromise/issues"},"homepage":"https://github.com/aheckmann/mpromise","_id":"mpromise@0.4.3","dist":{"shasum":"edc47a75a2a177b0e9382735db52dbec3808cc33","tarball":"http://registry.npmjs.org/mpromise/-/mpromise-0.4.3.tgz"},"_from":".","_npmVersion":"1.3.13","_npmUser":{"name":"refack","email":"refael@empeeric.com"},"maintainers":[{"name":"aaron","email":"aaron.heckmann+github@gmail.com"},{"name":"refack","email":"refael@empeeric.com"}],"directories":{}},"0.5.0-a":{"name":"mpromise","version":"0.5.0-a","description":"Promises A+ conformant implementation","main":"index.js","scripts":{"test":"node node_modules/mocha/bin/_mocha"},"devDependencies":{"longjohn":"~0.2.1","promises-aplus-tests":"~2.0.2","mocha":"~1.13.0"},"repository":{"type":"git","url":"git://github.com/aheckmann/mpromise"},"keywords":["promise","mongoose","aplus","a+","plus"],"author":{"name":"Aaron Heckmann","email":"aaron.heckmann+github@gmail.com"},"license":"MIT","bugs":{"url":"https://github.com/aheckmann/mpromise/issues"},"homepage":"https://github.com/aheckmann/mpromise","_id":"mpromise@0.5.0-a","dist":{"shasum":"ca55cfb3a0cee676704185fb634fa53aaf4f5c36","tarball":"http://registry.npmjs.org/mpromise/-/mpromise-0.5.0-a.tgz"},"_from":".","_npmVersion":"1.3.23","_npmUser":{"name":"refack","email":"refael@empeeric.com"},"maintainers":[{"name":"refack","email":"refael@empeeric.com"}],"directories":{}},"0.4.4":{"name":"mpromise","version":"0.4.4","description":"Promises A+ conformant implementation","main":"index.js","scripts":{"test":"node node_modules/mocha/bin/_mocha"},"devDependencies":{"longjohn":"0.2.2","promises-aplus-tests":"2.0.3","mocha":"1.13.0"},"repository":{"type":"git","url":"git://github.com/aheckmann/mpromise"},"keywords":["promise","mongoose","aplus","a+","plus"],"author":{"name":"Aaron Heckmann","email":"aaron.heckmann+github@gmail.com"},"license":"MIT","bugs":{"url":"https://github.com/aheckmann/mpromise/issues"},"homepage":"https://github.com/aheckmann/mpromise","_id":"mpromise@0.4.4","dist":{"shasum":"c8ae1b3972106ce149c23e06b9fa870e122398ba","tarball":"http://registry.npmjs.org/mpromise/-/mpromise-0.4.4.tgz"},"_from":".","_npmVersion":"1.3.23","_npmUser":{"name":"refack","email":"refael@empeeric.com"},"maintainers":[{"name":"refack","email":"refael@empeeric.com"}],"directories":{}},"0.5.1":{"name":"mpromise","version":"0.5.1","description":"Promises A+ conformant implementation","main":"index.js","scripts":{"test":"node node_modules/mocha/bin/_mocha"},"devDependencies":{"longjohn":"0.2.2","promises-aplus-tests":"2.0.3","mocha":"1.13.0"},"repository":{"type":"git","url":"git://github.com/aheckmann/mpromise"},"keywords":["promise","mongoose","aplus","a+","plus"],"author":{"name":"Aaron Heckmann","email":"aaron.heckmann+github@gmail.com"},"license":"MIT","bugs":{"url":"https://github.com/aheckmann/mpromise/issues"},"homepage":"https://github.com/aheckmann/mpromise","_id":"mpromise@0.5.1","dist":{"shasum":"ef1890a5c24e8b239f009474f0a65a040cca0e61","tarball":"http://registry.npmjs.org/mpromise/-/mpromise-0.5.1.tgz"},"_from":".","_npmVersion":"1.3.23","_npmUser":{"name":"refack","email":"refael@empeeric.com"},"maintainers":[{"name":"refack","email":"refael@empeeric.com"}],"directories":{}},"0.5.2":{"name":"mpromise","version":"0.5.2","publishConfig":{"tag":"beta"},"description":"Promises A+ conformant implementation","main":"lib/promise.js","scripts":{"test":"mocha"},"devDependencies":{"longjohn":"0.2.2","promises-aplus-tests":"2.0.3","mocha":"1.13.0"},"repository":{"type":"git","url":"git://github.com/aheckmann/mpromise"},"keywords":["promise","mongoose","aplus","a+","plus"],"author":{"name":"Aaron Heckmann","email":"aaron.heckmann+github@gmail.com"},"license":"MIT","bugs":{"url":"https://github.com/aheckmann/mpromise/issues"},"homepage":"https://github.com/aheckmann/mpromise","_id":"mpromise@0.5.2","dist":{"shasum":"f4f68a388d454177490c40e39bbd7ae89b6c08b7","tarball":"http://registry.npmjs.org/mpromise/-/mpromise-0.5.2.tgz"},"_from":".","_npmVersion":"1.3.25","_npmUser":{"name":"refack","email":"refael@empeeric.com"},"maintainers":[{"name":"refack","email":"refael@empeeric.com"}],"directories":{}},"0.5.3":{"name":"mpromise","version":"0.5.3","publishConfig":{"tag":"beta"},"description":"Promises A+ conformant implementation","main":"lib/promise.js","scripts":{"test":"mocha"},"devDependencies":{"promises-aplus-tests":"2.0.3","mocha":"1.17.1"},"repository":{"type":"git","url":"git://github.com/aheckmann/mpromise"},"keywords":["promise","mongoose","aplus","a+","plus"],"author":{"name":"Aaron Heckmann","email":"aaron.heckmann+github@gmail.com"},"license":"MIT","bugs":{"url":"https://github.com/aheckmann/mpromise/issues"},"homepage":"https://github.com/aheckmann/mpromise","_id":"mpromise@0.5.3","dist":{"shasum":"f634b62dba39ea5e30d11de467a95fa1153b9a4d","tarball":"http://registry.npmjs.org/mpromise/-/mpromise-0.5.3.tgz"},"_from":".","_npmVersion":"1.3.26","_npmUser":{"name":"refack","email":"refael@empeeric.com"},"maintainers":[{"name":"refack","email":"refael@empeeric.com"}],"directories":{}},"0.5.4":{"name":"mpromise","version":"0.5.4","publishConfig":{"tag":"beta"},"description":"Promises A+ conformant implementation","main":"lib/promise.js","scripts":{"test":"mocha"},"devDependencies":{"promises-aplus-tests":"2.0.3","mocha":"1.17.1"},"repository":{"type":"git","url":"git://github.com/aheckmann/mpromise"},"keywords":["promise","mongoose","aplus","a+","plus"],"author":{"name":"Aaron Heckmann","email":"aaron.heckmann+github@gmail.com"},"license":"MIT","bugs":{"url":"https://github.com/aheckmann/mpromise/issues"},"homepage":"https://github.com/aheckmann/mpromise","_id":"mpromise@0.5.4","dist":{"shasum":"b610613ec6de37419f944b35f0783b4de9f5dc75","tarball":"http://registry.npmjs.org/mpromise/-/mpromise-0.5.4.tgz"},"_from":".","_npmVersion":"1.3.26","_npmUser":{"name":"refack","email":"refael@empeeric.com"},"maintainers":[{"name":"aaron","email":"aaron.heckmann+github@gmail.com"},{"name":"refack","email":"refael@empeeric.com"}],"directories":{}}},"readme":"ERROR: No README data found!","maintainers":[{"name":"aaron","email":"aaron.heckmann+github@gmail.com"},{"name":"refack","email":"refael@empeeric.com"}],"time":{"modified":"2014-02-08T20:29:44.234Z","created":"2013-01-08T00:00:36.660Z","0.0.1":"2013-01-08T00:00:37.340Z","0.1.0":"2013-01-08T20:23:20.388Z","0.2.0":"2013-01-09T17:40:26.799Z","0.2.1":"2013-02-09T22:45:54.577Z","0.2.2":"2013-04-22T21:04:02.484Z","0.3.0":"2013-07-25T18:18:28.790Z","0.4.0":"2013-10-24T16:33:49.740Z","0.4.1":"2013-10-26T17:42:20.708Z","0.4.2":"2013-11-26T09:00:28.058Z","0.5.0":"2013-12-14T22:17:10.674Z","0.4.3":"2013-12-18T06:31:38.458Z","0.5.0-a":"2014-01-15T12:39:30.240Z","0.4.4":"2014-01-20T18:09:13.461Z","5.0.1":"2014-01-20T18:15:11.689Z","0.5.1":"2014-01-20T18:20:03.147Z","0.5.2":"2014-01-25T23:45:57.208Z","0.5.3":"2014-02-06T14:16:52.803Z","0.5.4":"2014-02-08T20:29:44.233Z"},"author":{"name":"Aaron Heckmann","email":"aaron.heckmann+github@gmail.com"},"repository":{"type":"git","url":"git://github.com/aheckmann/mpromise"},"readmeFilename":"README.md","_attachments":{},"_etag":"\"EKSULBDR8TYS5IX37OIMI7WOG\""}